pastacopy/__init__.py
pastacopy/clipboard_to_markdown.py
pastacopy-0.1.5.dist-info/METADATA
pastacopy-0.1.5.dist-info/WHEEL
pastacopy-0.1.5.dist-info/top_level.txt
pastacopy-0.1.5.dist-info/RECORD
